hydra_router/__init__.py
hydra_router/client/HydraClient.py
hydra_router/client/HydraClientPing.py
hydra_router/client/__init__.py
hydra_router/constants/DHydra.py
hydra_router/constants/__init__.py
hydra_router/server/HydraServer.py
hydra_router/server/HydraServerPong.py
hydra_router/server/__init__.py
hydra_router/utils/HydraLog.py
hydra_router/utils/HydraMsg.py
hydra_router/utils/__init__.py
hydra_router-0.14.0.dist-info/METADATA
hydra_router-0.14.0.dist-info/WHEEL
hydra_router-0.14.0.dist-info/entry_points.txt
hydra_router-0.14.0.dist-info/RECORD
