Metadata-Version: 2.4
Name: hydra-router
Version: 0.14.0
Summary: ZeroMQ-based distributed framework
Author: Nadim-Daniel Ghaznavi
Author-email: nghaznavi@gmail.com
Requires-Python: >=3.11,<4.0
Classifier: Programming Language :: Python :: 3
Classifier: Programming Language :: Python :: 3.11
Classifier: Programming Language :: Python :: 3.12
Classifier: Programming Language :: Python :: 3.13
Classifier: Programming Language :: Python :: 3.14
Requires-Dist: pyzmq (>=25.0.0,<26.0.0)
